LICENSE
MANIFEST.in
README.rst
setup.py
dmdd/__init__.py
dmdd/constants.py
dmdd/dmdd.py
dmdd/dmdd_efficiencies.pyx
dmdd/dmdd_plot.py
dmdd/formNR.pyx
dmdd/formUV.pyx
dmdd/formgenNR.pyx
dmdd/globals.py
dmdd/helpers.pyx
dmdd/rate_NR.pyx
dmdd/rate_UV.pyx
dmdd/rate_genNR.pyx
dmdd.egg-info/PKG-INFO
dmdd.egg-info/SOURCES.txt
dmdd.egg-info/dependency_links.txt
dmdd.egg-info/not-zip-safe
dmdd.egg-info/requires.txt
dmdd.egg-info/top_level.txt
dmdd/tests/__init__.py
dmdd/tests/test.py