Metadata-Version: 1.1
Name: dmdd
Version: 0.2
Summary: Enables simple simulation and Bayesian posterior analysis of recoil-event data from dark-matter direct-detection experiments under a wide variety of scattering theories. 
Home-page: https://github.com/veragluscevic/dmdd_2014
Author: V. Gluscevic, S. D. McDermott
Author-email: verag@ias.edu
License: UNKNOWN
Platform: UNKNOWN
Classifier: Development Status :: 3 - Alpha
Classifier: Intended Audience :: Science/Research
Classifier: Operating System :: OS Independent
Classifier: Programming Language :: Python
Classifier: Topic :: Scientific/Engineering
Classifier: Topic :: Scientific/Engineering :: Physics
